ptdeco/__init__.py
ptdeco/_version.py
ptdeco/py.typed
ptdeco/dwain/__init__.py
ptdeco/dwain/decomposition.py
ptdeco/falor/__init__.py
ptdeco/falor/decomposition.py
ptdeco/lockd/__init__.py
ptdeco/lockd/decomposition.py
ptdeco/lockd/losses.py
ptdeco/utils/__init__.py
ptdeco/utils/common.py
ptdeco/utils/losses_primitives.py
ptdeco/utils/modconfig.py
ptdeco-0.5.0.dist-info/LICENSE
ptdeco-0.5.0.dist-info/METADATA
ptdeco-0.5.0.dist-info/WHEEL
ptdeco-0.5.0.dist-info/top_level.txt
ptdeco-0.5.0.dist-info/RECORD
