Metadata-Version: 2.1
Name: ptdeco
Version: 0.5.0
Summary: ptdeco is a library implementing decomposition algorithms for model optimization.
Author: TCL Research Europe
License: 
Classifier: Programming Language :: Python :: 3
Requires-Python: >=3.10
License-File: LICENSE
Requires-Dist: torch
Requires-Dist: numpy
